altmethods.py
eeoptimizer.py
eeutility.py
eecr/__init__.py
eecr/altmethods.py
eecr/cstree.py
eecr/dcamodel.py
eecr/eeoptimizer.py
eecr/eeutility.py
eecr/generators.py
eecr/sample_code.py
eecr/scamodel.py
eecr/sharingtree.py
eecr/simpletree.py
eecr/tester.py
eecr/Datasets/SHL_config
eecr/Datasets/SHL_data
eecr-0.0.1.dist-info/LICENSE
eecr-0.0.1.dist-info/METADATA
eecr-0.0.1.dist-info/WHEEL
eecr-0.0.1.dist-info/top_level.txt
eecr-0.0.1.dist-info/RECORD
