Metadata-Version: 2.1
Name: eecr
Version: 0.0.1
Summary: Tools for the optimization of energy in a context recognition task
Home-page: https://github.com/VitoJanko/Energy-Efficient-Context-Recognition
Author: Vito Janko
Author-email: vito.janko@ijs.si
License: UNKNOWN
Project-URL: Documentation, https://dis.ijs.si/eecr/
Keywords: context recognition awareness classification energy consumption optimization
Platform: UNKNOWN
Classifier: Programming Language :: Python :: 3
Classifier: Programming Language :: Python :: 3.6
Classifier: Programming Language :: Python :: 3.7
Classifier: Development Status :: 4 - Beta
Classifier: License :: OSI Approved :: MIT License
Classifier: Operating System :: OS Independent
Requires-Python: >=3
Requires-Dist: scikit-learn
Requires-Dist: deap
Requires-Dist: pandas
Requires-Dist: numpy
Requires-Dist: matplotlib
